decisionlib_cli/__init__.py
decisionlib_cli/hook.py
decisionlib_cli/shell.py
decisionlib_cli_mhentges-0.0.6.dist-info/METADATA
decisionlib_cli_mhentges-0.0.6.dist-info/WHEEL
decisionlib_cli_mhentges-0.0.6.dist-info/entry_points.txt
decisionlib_cli_mhentges-0.0.6.dist-info/top_level.txt
decisionlib_cli_mhentges-0.0.6.dist-info/RECORD
